{
	"name": "energy_hrly_stg",
	"properties": {
		"linkedServiceName": {
			"referenceName": "AzureDataLakeStorage1",
			"type": "LinkedServiceReference"
		},
		"folder": {
			"name": "energy_datasets/storage_ds"
		},
		"annotations": [],
		"type": "Json",
		"typeProperties": {
			"location": {
				"type": "AzureBlobFSLocation",
				"fileName": {
					"value": "@concat('energy_hrly_', utcnow('yyyyMMdd'))",
					"type": "Expression"
				},
				"folderPath": "energy_hrly/input",
				"fileSystem": "bronze"
			}
		},
		"schema": {}
	},
	"type": "Microsoft.DataFactory/factories/datasets"
}